<?xml version="1.0"?>
<!DOCTYPE hibernate-mapping PUBLIC "-//Hibernate/Hibernate Mapping DTD 3.0//EN"
"http://www.hibernate.org/dtd/hibernate-mapping-3.0.dtd">
<!-- Generated 26/02/2016 11:17:08 AM by Hibernate Tools 4.3.1.Final -->
<hibernate-mapping>
    <class name="co.edu.usbcali.demo.modelo.VtPrioridad" table="vt_prioridad" schema="public" optimistic-lock="version">
        <comment>MUY ALTA ALTA MEDIA BAJA MUY BAJA</comment>
        <id name="prioCodigo" type="java.lang.Long">
            <column name="prio_codigo" />
            <generator class="assigned" />
        </id>
        <property name="nombre" type="java.lang.String">
            <column name="nombre" not-null="true" />
        </property>
        <property name="fechaCreacion" type="java.util.Date">
            <column name="fecha_creacion" length="29" not-null="true" />
        </property>
        <property name="fechaModificacion" type="java.util.Date">
            <column name="fecha_modificacion" length="29" />
        </property>
        <property name="usuCreador" type="java.lang.Long">
            <column name="usu_creador" not-null="true" />
        </property>
        <property name="usuModificador" type="java.lang.Long">
            <column name="usu_modificador" />
        </property>
        <property name="activo" type="java.lang.String">
            <column name="activo" length="1" not-null="true" />
        </property>
        <set name="vtArtefactos" table="vt_artefacto" inverse="true" lazy="true" fetch="select">
            <key>
                <column name="prio_codigo" not-null="true" />
            </key>
            <one-to-many class="co.edu.usbcali.demo.modelo.VtArtefacto" />
        </set>
    </class>
</hibernate-mapping>
